LICENSE
README.md
setup.cfg
setup.py
tornado_ipware/__init__.py
tornado_ipware/defaults.py
tornado_ipware/ip.py
tornado_ipware/utils.py
tornado_ipware.egg-info/PKG-INFO
tornado_ipware.egg-info/SOURCES.txt
tornado_ipware.egg-info/dependency_links.txt
tornado_ipware.egg-info/top_level.txt
tornado_ipware/__pycache__/__init__.cpython-39.pyc
tornado_ipware/__pycache__/defaults.cpython-39.pyc
tornado_ipware/__pycache__/ip.cpython-39.pyc
tornado_ipware/__pycache__/utils.cpython-39.pyc
tornado_ipware/tests/__init__.py
tornado_ipware/tests/tests_common.py
tornado_ipware/tests/tests_ipv4.py
tornado_ipware/tests/tests_ipv6.py
tornado_ipware/tests/__pycache__/__init__.cpython-39.pyc
tornado_ipware/tests/__pycache__/tests_common.cpython-39.pyc
tornado_ipware/tests/__pycache__/tests_ipv4.cpython-39.pyc
tornado_ipware/tests/__pycache__/tests_ipv6.cpython-39.pyc