Metadata-Version: 1.1
Name: tornado-ipware
Version: 1.0
Summary: A Tornado utility application that returns client's real IP address
Home-page: https://github.com/lumbrefrio/tornado-ipware
Author: Bill Batey
Author-email: lumbrefrio@gmail.com
License: MIT
Platform: UNKNOWN
Classifier: Development Status :: 5 - Production/Stable
Classifier: Environment :: Web Environment
Classifier: Intended Audience :: Developers
Classifier: License :: OSI Approved :: MIT License
Classifier: Operating System :: OS Independent
Classifier: Programming Language :: Python
Classifier: Programming Language :: Python :: 3.5
Classifier: Programming Language :: Python :: 3.6
Classifier: Programming Language :: Python :: 3.7
Classifier: Programming Language :: Python :: 3.8
Classifier: Topic :: Utilities
